polars_fuzzy_match-0.1.5.dist-info/METADATA
polars_fuzzy_match-0.1.5.dist-info/WHEEL
polars_fuzzy_match-0.1.5.dist-info/license_files/LICENSE
polars_fuzzy_match/util.py
polars_fuzzy_match/__init__.py
polars_fuzzy_match/polars_fuzzy_match.abi3.so
polars_fuzzy_match-0.1.5.dist-info/RECORD
