Metadata-Version: 2.3
Name: polars-fuzzy-match
Version: 0.1.5
Classifier: Programming Language :: Rust
Classifier: Programming Language :: Python :: Implementation :: CPython
Classifier: Programming Language :: Python :: Implementation :: PyPy
License-File: LICENSE
Summary: Polars extension for fzf-style fuzzy matching 
Requires-Python: >=3.8
Project-URL: Repository, https://github.com/bnm3k/polars-fuzzy-match
Project-URL: Documentation, https://github.com/bnm3k/polars-fuzzy-match/blob/master/README.md
Project-URL: Change Log, https://github.com/bnm3k/polars-fuzzy-match/releases
Project-URL: Issue Tracker, https://github.com/bnm3k/polars-fuzzy-match/issues
